{
  "recommendations": [
    {
      "uvIndexRange": [0, 2],
      "payung": "Diperlukan",
      "luarRuangan": "Aman",
      "indeksUV": "Rendah",
      "pakaian": "Gunakan pakaian yang nyaman dan berlapis",
      "sengatanPanas": "Aman",
      "anginDingin": "Ekstrem",
      "mendaki": "Aman",
      "lari": "Aman",
      "piknik": "Aman",
      "melihatBintang": "Aman",
      "bersepeda": "Aman",
      "berkebun": "Aman",
      "dpayung": "Diperlukan - Sediakan payung untuk perlindungan tambahan",
      "dluarRuangan": "Aman - Aktivitas luar ruangan dapat dilakukan dengan nyaman",
      "dindeksUV": "Rendah - Indeks UV berada pada tingkat rendah",
      "dpakaian": "Gunakan pakaian yang nyaman dan berlapis",
      "dsengatanPanas": "Aman - Risiko sengatan panas rendah",
      "danginDingin": "Ekstrem - Waspada terhadap angin dingin ekstrem",
      "dmendaki": "Aman - Gunakan perlengkapan standar, tetap waspada terhadap cuaca",
      "dlari": "Aman - Jaga ritme dan hindari berlari di bawah sinar matahari langsung",
      "dpiknik": "Aman - Nikmati waktu piknik dengan perlindungan sinar matahari",
      "dmelihatBintang": "Aman - Nikmati melihat bintang di malam hari",
      "dbersepeda": "Aman - Nikmati bersepeda dengan perlindungan sinar matahari",
      "dberkebun": "Aman - Lakukan kegiatan berkebun dengan perlindungan sinar matahari"
    },
    {
      "uvIndexRange": [3, 5],
      "indeksUV": "Sedang",
      "payung": "Diperlukan",
      "luarRuangan": "Kurang",
      "sengatanPanas": "Bahaya",
      "anginDingin": "Aman",
      "pakaian": "Gunakan pakaian yang nyaman, berlapis, dan pelindung",
      "mendaki": "Aman",
      "lari": "Aman",
      "piknik": "Aman",
      "melihatBintang": "Aman",
      "bersepeda": "Aman",
      "berkebun": "Aman",
      "dindeksUV": "Sedang - Indeks UV berada pada tingkat sedang",
      "dpayung": "Diperlukan - Sediakan payung untuk perlindungan tambahan",
      "dluarRuangan": "Kurang Aman - Pertimbangkan untuk mengurangi aktivitas luar ruangan",
      "dsengatanPanas": "Bahaya - Gunakan tabir surya, topi, dan pakaian pelindung",
      "danginDingin": "Aman - Waspada terhadap angin dingin",
      "dpakaian": "Gunakan pakaian yang nyaman, berlapis, dan pelindung",
      "dmendaki": "Aman - Tetap waspada terhadap suhu dan kenakan perlengkapan standar",
      "dlari": "Aman - Hindari berlari di bawah sinar matahari langsung",
      "dpiknik": "Aman - Gunakan payung atau cari tempat teduh",
      "dmelihatBintang": "Aman - Nikmati melihat bintang di malam hari",
      "dbersepeda": "Aman - Gunakan tabir surya dan pakaian pelindung",
      "dberkebun": "Aman - Lakukan kegiatan berkebun dengan perlindungan sinar matahari"
    },
    {
      "uvIndexRange": [6, 7],
      "indeksUV": "Tinggi",
      "payung": "Diperlukan",
      "luarRuangan": "Sangat Kurang",
      "sengatanPanas": "Bahaya",
      "anginDingin": "Aman",
      "pakaian": "Gunakan pakaian yang nyaman, berlapis, dan pelindung",
      "mendaki": "Kurang Aman",
      "lari": "Aman",
      "piknik": "Kurang Aman",
      "melihatBintang": "Aman",
      "bersepeda": "Aman",
      "berkebun": "Aman",
      "dindeksUV": "Tinggi - Indeks UV berada pada tingkat tinggi",
      "dpayung": "Diperlukan - Sediakan payung untuk perlindungan tambahan",
      "dluarRuangan": "Sangat Kurang Aman - Pertimbangkan untuk mengurangi aktivitas luar ruangan",
      "dsengatanPanas": "Bahaya - Gunakan tabir surya, topi, dan pakaian pelindung",
      "danginDingin": "Aman - Waspada terhadap angin dingin",
      "dpakaian": "Gunakan pakaian yang nyaman, berlapis, dan pelindung",
      "dmendaki": "Kurang Aman - Pertimbangkan untuk tidak mendaki pada tingkat UV tinggi",
      "dlari": "Aman - Hindari berlari di bawah sinar matahari langsung",
      "dpiknik": "Kurang Aman - Hindari beraktivitas di luar pada tingkat UV tinggi",
      "dmelihatBintang": "Aman - Nikmati melihat bintang di malam hari",
      "dbersepeda": "Aman - Gunakan tabir surya dan pakaian pelindung",
      "dberkebun": "Aman - Lakukan kegiatan berkebun dengan perlindungan sinar matahari"
    },
    {
      "uvIndexRange": [8, 10],
      "indeksUV": "Sangat Tinggi",
      "payung": "Diperlukan",
      "luarRuangan": "Sangat Kurang",
      "sengatanPanas": "Bahaya",
      "anginDingin": "Aman",
      "pakaian": "Gunakan pakaian yang nyaman, berlapis, pelindung",
      "mendaki": "Bahaya",
      "lari": "Kurang Aman",
      "piknik": "Kurang Aman",
      "melihatBintang": "Aman",
      "bersepeda": "Kurang Aman",
      "berkebun": "Aman",
      "dindeksUV": "Sangat Tinggi - Indeks UV berada pada tingkat sangat tinggi",
      "dpayung": "Diperlukan - Sediakan payung untuk perlindungan tambahan",
      "dluarRuangan": "Sangat Kurang Aman - Pertimbangkan untuk mengurangi aktivitas luar ruangan",
      "dsengatanPanas": "Bahaya - Gunakan tabir surya, topi, dan pakaian pelindung",
      "danginDingin": "Aman - Waspada terhadap angin dingin",
      "dpakaian": "Gunakan pakaian yang nyaman, berlapis, dan pelindung",
      "dmendaki": "Bahaya - Hindari mendaki pada tingkat UV sangat tinggi",
      "dlari": "Kurang Aman - Hindari berlari di bawah sinar matahari langsung",
      "dpiknik": "Kurang Aman - Hindari beraktivitas di luar pada tingkat UV sangat tinggi",
      "dmelihatBintang": "Aman - Hindari melihat bintang pada tingkat UV sangat tinggi",
      "dbersepeda": "Kurang Aman - Gunakan tabir surya dan pakaian pelindung",
      "dberkebun": "Aman - Lakukan kegiatan berkebun dengan perlindungan sinar matahari"
    },
    {
      "uvIndexRange": [11, 9999],
      "indeksUV": "Ekstrem",
      "payung": "Diperlukan",
      "luarRuangan": "Sangat Kurang",
      "sengatanPanas": "Bahaya",
      "anginDingin": "Ekstrem",
      "pakaian": "Gunakan pakaian yang nyaman, berlapis, serta topi",
      "mendaki": "Bahaya",
      "lari": "Kurang Aman",
      "piknik": "Kurang Aman",
      "melihatBintang": "Sangat Buruk",
      "bersepeda": "Kurang Aman",
      "berkebun": "Kurang Aman",
      "dindeksUV": "Ekstrem - Indeks UV berada pada tingkat ekstrem",
      "dpayung": "Diperlukan - Sediakan payung untuk perlindungan tambahan",
      "dluarRuangan": "Sangat Kurang Aman - Pertimbangkan untuk mengurangi aktivitas luar ruangan",
      "dsengatanPanas": "Bahaya - Gunakan tabir surya, topi, dan pakaian pelindung",
      "danginDingin": "Ekstrem - Waspada terhadap angin dingin",
      "dpakaian": "Gunakan pakaian yang nyaman, berlapis, serta topi",
      "dmendaki": "Bahaya - Hindari mendaki pada tingkat UV ekstrem",
      "dlari": "Kurang Aman - Hindari berlari di bawah sinar matahari langsung",
      "dpiknik": "Kurang Aman - Hindari beraktivitas di luar pada tingkat UV ekstrem",
      "dmelihatBintang": "Sangat Buruk - Hindari melihat bintang pada tingkat UV ekstrem",
      "dbersepeda": "Kurang Aman - Gunakan tabir surya dan pakaian pelindung",
      "dberkebun": "Kurang Aman - Lakukan kegiatan berkebun dengan perlindungan sinar matahari"
    }
  ]
}
